<?xml version='1.0' encoding='utf-8'?>
<TextureAtlas imagePath="myra.png"><SubTexture name="myra down0000" x="0" y="0" width="1506" height="1454" frameX="0" frameY="0" frameWidth="1506" frameHeight="1454" />
<SubTexture name="myra down0001" x="1506" y="0" width="1506" height="1454" frameX="0" frameY="0" frameWidth="1506" frameHeight="1454" />
<SubTexture name="myra down0002" x="3012" y="0" width="1506" height="1454" frameX="0" frameY="0" frameWidth="1506" frameHeight="1454" />
<SubTexture name="myra down0003" x="4518" y="0" width="1506" height="1454" frameX="0" frameY="0" frameWidth="1506" frameHeight="1454" />
<SubTexture name="myra down0004" x="6024" y="0" width="1506" height="1454" frameX="0" frameY="0" frameWidth="1506" frameHeight="1454" />
<SubTexture name="myra down0005" x="7530" y="0" width="1506" height="1454" frameX="0" frameY="0" frameWidth="1506" frameHeight="1454" />
<SubTexture name="myra down0006" x="0" y="1454" width="1506" height="1454" frameX="0" frameY="0" frameWidth="1506" frameHeight="1454" />
<SubTexture name="myra down0007" x="1506" y="1454" width="1506" height="1454" frameX="0" frameY="0" frameWidth="1506" frameHeight="1454" />
<SubTexture name="myra down0008" x="3012" y="1454" width="1506" height="1454" frameX="0" frameY="0" frameWidth="1506" frameHeight="1454" />
<SubTexture name="myra idle0000" x="4518" y="1454" width="1304" height="1304" frameX="0" frameY="0" frameWidth="1304" frameHeight="1304" />
<SubTexture name="myra idle0001" x="5822" y="1454" width="1304" height="1304" frameX="0" frameY="0" frameWidth="1304" frameHeight="1304" />
<SubTexture name="myra idle0002" x="7126" y="1454" width="1304" height="1304" frameX="0" frameY="0" frameWidth="1304" frameHeight="1304" />
<SubTexture name="myra idle0003" x="0" y="2908" width="1304" height="1304" frameX="0" frameY="0" frameWidth="1304" frameHeight="1304" />
<SubTexture name="myra idle0004" x="1304" y="2908" width="1304" height="1304" frameX="0" frameY="0" frameWidth="1304" frameHeight="1304" />
<SubTexture name="myra idle0005" x="2608" y="2908" width="1304" height="1304" frameX="0" frameY="0" frameWidth="1304" frameHeight="1304" />
<SubTexture name="myra idle0006" x="3912" y="2908" width="1304" height="1304" frameX="0" frameY="0" frameWidth="1304" frameHeight="1304" />
<SubTexture name="myra idle0007" x="5216" y="2908" width="1304" height="1304" frameX="0" frameY="0" frameWidth="1304" frameHeight="1304" />
<SubTexture name="myra idle0008" x="6520" y="2908" width="1304" height="1304" frameX="0" frameY="0" frameWidth="1304" frameHeight="1304" />
<SubTexture name="myra idle0009" x="0" y="4212" width="1304" height="1304" frameX="0" frameY="0" frameWidth="1304" frameHeight="1304" />
<SubTexture name="myra idle0010" x="1304" y="4212" width="1304" height="1304" frameX="0" frameY="0" frameWidth="1304" frameHeight="1304" />
<SubTexture name="myra idle0011" x="2608" y="4212" width="1304" height="1304" frameX="0" frameY="0" frameWidth="1304" frameHeight="1304" />
<SubTexture name="myra left0000" x="3912" y="4212" width="1501" height="1454" frameX="0" frameY="0" frameWidth="1501" frameHeight="1454" />
<SubTexture name="myra left0001" x="5413" y="4212" width="1501" height="1454" frameX="0" frameY="0" frameWidth="1501" frameHeight="1454" />
<SubTexture name="myra left0002" x="6914" y="4212" width="1501" height="1454" frameX="0" frameY="0" frameWidth="1501" frameHeight="1454" />
<SubTexture name="myra left0003" x="0" y="5666" width="1501" height="1454" frameX="0" frameY="0" frameWidth="1501" frameHeight="1454" />
<SubTexture name="myra left0004" x="1501" y="5666" width="1501" height="1454" frameX="0" frameY="0" frameWidth="1501" frameHeight="1454" />
<SubTexture name="myra left0005" x="3002" y="5666" width="1501" height="1454" frameX="0" frameY="0" frameWidth="1501" frameHeight="1454" />
<SubTexture name="myra left0006" x="4503" y="5666" width="1501" height="1454" frameX="0" frameY="0" frameWidth="1501" frameHeight="1454" />
<SubTexture name="myra left0007" x="6004" y="5666" width="1501" height="1454" frameX="0" frameY="0" frameWidth="1501" frameHeight="1454" />
<SubTexture name="myra left0008" x="7505" y="5666" width="1501" height="1454" frameX="0" frameY="0" frameWidth="1501" frameHeight="1454" />
<SubTexture name="myra right0000" x="0" y="7120" width="1906" height="1454" frameX="0" frameY="0" frameWidth="1906" frameHeight="1454" />
<SubTexture name="myra right0001" x="1906" y="7120" width="1906" height="1454" frameX="0" frameY="0" frameWidth="1906" frameHeight="1454" />
<SubTexture name="myra right0002" x="3812" y="7120" width="1906" height="1454" frameX="0" frameY="0" frameWidth="1906" frameHeight="1454" />
<SubTexture name="myra right0003" x="5718" y="7120" width="1906" height="1454" frameX="0" frameY="0" frameWidth="1906" frameHeight="1454" />
<SubTexture name="myra right0004" x="7624" y="7120" width="1906" height="1454" frameX="0" frameY="0" frameWidth="1906" frameHeight="1454" />
<SubTexture name="myra right0005" x="9530" y="7120" width="1906" height="1454" frameX="0" frameY="0" frameWidth="1906" frameHeight="1454" />
<SubTexture name="myra right0006" x="0" y="8574" width="1906" height="1454" frameX="0" frameY="0" frameWidth="1906" frameHeight="1454" />
<SubTexture name="myra right0007" x="1906" y="8574" width="1906" height="1454" frameX="0" frameY="0" frameWidth="1906" frameHeight="1454" />
<SubTexture name="myra right0008" x="3812" y="8574" width="1906" height="1454" frameX="0" frameY="0" frameWidth="1906" frameHeight="1454" />
<SubTexture name="myra up0000" x="5718" y="8574" width="1576" height="1604" frameX="0" frameY="0" frameWidth="1576" frameHeight="1604" />
<SubTexture name="myra up0001" x="7294" y="8574" width="1576" height="1604" frameX="0" frameY="0" frameWidth="1576" frameHeight="1604" />
<SubTexture name="myra up0002" x="8870" y="8574" width="1576" height="1604" frameX="0" frameY="0" frameWidth="1576" frameHeight="1604" />
<SubTexture name="myra up0003" x="0" y="10178" width="1576" height="1604" frameX="0" frameY="0" frameWidth="1576" frameHeight="1604" />
<SubTexture name="myra up0004" x="1576" y="10178" width="1576" height="1604" frameX="0" frameY="0" frameWidth="1576" frameHeight="1604" />
<SubTexture name="myra up0005" x="3152" y="10178" width="1576" height="1604" frameX="0" frameY="0" frameWidth="1576" frameHeight="1604" />
<SubTexture name="myra up0006" x="4728" y="10178" width="1576" height="1604" frameX="0" frameY="0" frameWidth="1576" frameHeight="1604" />
<SubTexture name="myra up0007" x="6304" y="10178" width="1576" height="1604" frameX="0" frameY="0" frameWidth="1576" frameHeight="1604" />
<SubTexture name="myra up0008" x="7880" y="10178" width="1576" height="1604" frameX="0" frameY="0" frameWidth="1576" frameHeight="1604" />
</TextureAtlas>
